knexus-0.0.1.dist-info/licenses/LICENSE
nexus/__init__.py
nexus/_C/libnexus-api.so
nexus/_C/libnexus.so
nexus/device_lib/amd-gpu-gfx942.json
nexus/device_lib/amd-gpu-gfx950.json
nexus/device_lib/apple-gpu-.json
nexus/device_lib/apple-gpu-applegpu_g16s.json
nexus/device_lib/apple-gpu-m1m.json
nexus/device_lib/apple-gpu-m2.json
nexus/device_lib/apple-gpu-m3.json
nexus/device_lib/apple-gpu-m4.json
nexus/device_lib/apple-gpu-m4p.json
nexus/device_lib/nvidia-gpu-sm_90.json
nexus/runtime_libs/libcpu_plugin.so
nexus/runtime_libs/libcuda_plugin.so
knexus-0.0.1.dist-info/METADATA
knexus-0.0.1.dist-info/WHEEL
knexus-0.0.1.dist-info/top_level.txt
knexus-0.0.1.dist-info/RECORD
