Metadata-Version: 2.4
Name: knexus
Version: 0.0.1
Home-page: https://github.com/kernelize-ai/nexus/
Author: Simon Waters
Author-email: simon@kernelize.ai
Keywords: Runtime,Triton
Classifier: Development Status :: 4 - Beta
Classifier: Intended Audience :: Developers
Classifier: Topic :: Software Development :: Build Tools
Classifier: License :: OSI Approved :: MIT License
Classifier: Programming Language :: Python :: 3.9
Classifier: Programming Language :: Python :: 3.10
Classifier: Programming Language :: Python :: 3.11
Classifier: Programming Language :: Python :: 3.12
Classifier: Programming Language :: Python :: 3.13
Requires-Python: >=3.9,<3.14
License-File: LICENSE
Requires-Dist: setuptools>=40.8.0
Requires-Dist: importlib-metadata; python_version < "3.10"
Provides-Extra: test
Requires-Dist: pytest>=6.0; extra == "test"
Dynamic: author
Dynamic: author-email
Dynamic: classifier
Dynamic: home-page
Dynamic: keywords
Dynamic: license-file
Dynamic: provides-extra
Dynamic: requires-dist
Dynamic: requires-python
